slot/__init__.py
slot/cli/__init__.hy
slot/cli/list.hy
slot/cli/options.hy
slot/cli/stores/__init__.hy
slot/cli/stores/create.hy
slot/cli/stores/ingest.hy
slot/cli/use.hy
slot/config.hy
slot/constants.hy
slot/exceptions.hy
slot/store.hy
slot/utils.hy
slot-0.3.0.dist-info/entry_points.txt
slot-0.3.0.dist-info/WHEEL
slot-0.3.0.dist-info/METADATA
slot-0.3.0.dist-info/RECORD
