Metadata-Version: 2.1
Name: slot
Version: 0.3.0
Summary: Rotate your files via symlink
Home-page: https://github.com/markrawls/slot
Author: Mark Rawls
Author-email: markrawls96@gmail.com
Requires-Python: >=3.7,<4.0
Classifier: Programming Language :: Python :: 3
Classifier: Programming Language :: Python :: 3.7
Classifier: Programming Language :: Python :: 3.8
Classifier: Programming Language :: Python :: 3.9
Requires-Dist: click (>=7.1.2,<8.0.0)
Requires-Dist: colorama (>=0.4.3,<0.5.0)
Requires-Dist: hy (>=0.19.0,<0.20.0)
Requires-Dist: importlib-metadata (>=1.7.0,<2.0.0)
Requires-Dist: python-box (>=5.1.0,<6.0.0)
Requires-Dist: ruamel.yaml (>=0.16.10,<0.17.0)
Requires-Dist: use-dir (>=0.1.4,<0.2.0)
Project-URL: Repository, https://github.com/markrawls/slot
